pyilper/__init__.py
pyilper/lifcore.py
pyilper/lifexec.py
pyilper/lifutils.py
pyilper/penconfig.py
pyilper/pilbox.py
pyilper/pilcharconv.py
pyilper/pilconfig.py
pyilper/pilcore.py
pyilper/pildevbase.py
pyilper/pildrive.py
pyilper/pilhp2225b.py
pyilper/pilhp82162a.py
pyilper/pilkeymap.py
pyilper/pilpdf.py
pyilper/pilplotter.py
pyilper/pilprinter.py
pyilper/pilqterm.py
pyilper/pilrs232.py
pyilper/pilscope.py
pyilper/pilsocket.py
pyilper/piltcpip.py
pyilper/pilterminal.py
pyilper/pilthreads.py
pyilper/pilwidgets.py
pyilper/pyilpermain.py
pyilper/shortcutconfig.py
pyilper/userconfig.py
pyilper/Manual/changelog.html
pyilper/Manual/drive.html
pyilper/Manual/filemenu.html
pyilper/Manual/helpmenu.html
pyilper/Manual/hp2225b.html
pyilper/Manual/hp82162a.html
pyilper/Manual/index.html
pyilper/Manual/interface.html
pyilper/Manual/introduction.html
pyilper/Manual/license.html
pyilper/Manual/miscellaneous.html
pyilper/Manual/parameters.html
pyilper/Manual/plotter.html
pyilper/Manual/printer.html
pyilper/Manual/rawdrive.html
pyilper/Manual/releasenotes.html
pyilper/Manual/scope.html
pyilper/Manual/startup.html
pyilper/Manual/terminal.html
pyilper/Manual/troubleshooting.html
pyilper/Manual/utilitiesmenu.html
pyilper/Manual/css/w3-theme-black.css
pyilper/Manual/css/w3.css
pyilper/lifimage/CASSETTE.DAT
pyilper/lifimage/FLOPPY.DAT
pyilper/lifimage/HDRIVE1.DAT
pyilper/lifimage/HDRIVE16.DAT
pyilper/lifimage/HDRIVE2.DAT
pyilper/lifimage/HDRIVE4.DAT
pyilper/lifimage/HDRIVE8.DAT
pyilper/lifimage/PILIMAGE.DAT
pyilper/lifimage/README.TXT
pyilper-1.8.10.dist-info/METADATA
pyilper-1.8.10.dist-info/WHEEL
pyilper-1.8.10.dist-info/entry_points.txt
pyilper-1.8.10.dist-info/licenses/AUTHORS
pyilper-1.8.10.dist-info/licenses/LICENSE
pyilper-1.8.10.dist-info/RECORD
